subito_client/__init__.py
subito_client/cli.py
subito_client/configs/__init__.py
subito_client/configs/config.py
subito_client/configs/config.yml
subito_client/translation/__init__.py
subito_client/translation/operations.py
subito_client/translation/pipeline.py
subito_client/utils/__init__.py
subito_client/utils/convert_to_srt.py
subito_client/utils/fix_rtl.py
subito_client/utils/srt_to_ass.py
subito_client-0.1.0.dist-info/METADATA
subito_client-0.1.0.dist-info/WHEEL
subito_client-0.1.0.dist-info/entry_points.txt
subito_client-0.1.0.dist-info/top_level.txt
subito_client-0.1.0.dist-info/RECORD
