Metadata-Version: 2.1
Name: subito-client
Version: 0.1.0
Summary: A subtitle translator that utilizes LLMs
Home-page: https://github.com/hernehunter/subito-client
Author: hernehunter
Author-email: h3rn3hunt3r@gmail.com
Classifier: Programming Language :: Python :: 3
Classifier: Operating System :: OS Independent
Requires-Python: >=3.7
Requires-Dist: PyYAML~=6.0.2
Requires-Dist: aiohttp~=3.11.12
Requires-Dist: websockets~=15.0
Requires-Dist: pysubs2~=1.8.0
Requires-Dist: setuptools~=75.6.0
Requires-Dist: pysrt~=1.1.2
